tengi/__init__.py
tengi/event.py
tengi/hasher.py
tengi/command/__init__.py
tengi/command/card.py
tengi/command/command_context.py
tengi/command/command_error.py
tengi/command/command_handler.py
tengi/command/command_hub.py
tengi/command/command_parser.py
tengi/command/handler_config.py
tengi/command/handler_essentials.py
tengi/command/handler_password.py
tengi/command/handler_pool.py
tengi/command/handler_send_message.py
tengi/command/param.py
tengi/command/tengi_command_params.py
tengi/command/tengine_command_params.py
tengi/csv_log/__init__.py
tengi/csv_log/csv_logger.py
tengi/csv_log/messages_logger.py
tengi/hack/__init__.py
tengi/hack/jsonstore_hack.py
tengi/setup/__init__.py
tengi/setup/app.py
tengi/setup/config.py
tengi/setup/config_utils.py
tengi/state/__init__.py
tengi/state/abuse_detector.py
tengi/state/abuse_janitor.py
tengi/state/chat_id_preserver.py
tengi/state/preserver.py
tengi/state/timed_preserver.py
tengi/telegram/__init__.py
tengi/telegram/constants.py
tengi/telegram/inbox_handler.py
tengi/telegram/inbox_hub.py
tengi/telegram/reply_context.py
tengi/telegram/telegram_api.py
tengi/telegram/telegram_api_utils.py
tengi/telegram/telegram_bot.py
tengi/telegram/telegram_bot_utils.py
tengi/telegram/telegram_cursor.py
tengi/telegram/telegram_error.py
tengi-0.5.8.dist-info/LICENSE
tengi-0.5.8.dist-info/METADATA
tengi-0.5.8.dist-info/WHEEL
tengi-0.5.8.dist-info/top_level.txt
tengi-0.5.8.dist-info/RECORD
