Metadata-Version: 2.1
Name: tengi
Version: 0.5.8
Summary: Telegram bot engine
Home-page: https://github.com/luckybots/tengi
Author: luckybots
Author-email: luckybots@protonmail.com
License: Apache License, Version 2.0
Project-URL: Bug Tracker, https://github.com/luckybots/tengi/issues
Platform: UNKNOWN
Classifier: Programming Language :: Python :: 3
Classifier: License :: OSI Approved :: Apache Software License
Classifier: Operating System :: OS Independent
Requires-Python: >=3.6
License-File: LICENSE
Requires-Dist: pymitter
Requires-Dist: pyTelegramBotAPI
Requires-Dist: python-jsonstore
Requires-Dist: Telethon
Requires-Dist: typeguard
